CHANGES.txt
README.txt
bootstrap.py
buildout.cfg
setup.py
src/zope/__init__.py
src/zope.app.locking.egg-info/PKG-INFO
src/zope.app.locking.egg-info/SOURCES.txt
src/zope.app.locking.egg-info/dependency_links.txt
src/zope.app.locking.egg-info/namespace_packages.txt
src/zope.app.locking.egg-info/not-zip-safe
src/zope.app.locking.egg-info/requires.txt
src/zope.app.locking.egg-info/top_level.txt
src/zope/app/__init__.py
src/zope/app/locking/README.txt
src/zope/app/locking/__init__.py
src/zope/app/locking/adapter.py
src/zope/app/locking/configure.zcml
src/zope/app/locking/interfaces.py
src/zope/app/locking/lockinfo.py
src/zope/app/locking/storage.py
src/zope/app/locking/tests.py